{
  "tripId": "bccb1dae-0ee2-422a-b40c-9b80c0dca12a",
  "scenarioId": "paris-rome-4d",
  "generatedAt": "2026-03-19T23:04:48.307Z",
  "destination": "Rome",
  "summary": {
    "totalIssues": 16,
    "critical": 1,
    "warning": 10,
    "info": 5,
    "score": 92,
    "weightedScore": 92
  },
  "sectionScores": {
    "schedule": {
      "score": 90,
      "critical": 1,
      "warning": 0,
      "info": 0,
      "totalIssues": 1,
      "weightedPenalty": 10
    },
    "geography": {
      "score": 76,
      "critical": 0,
      "warning": 4,
      "info": 0,
      "totalIssues": 4,
      "weightedPenalty": 24.15
    },
    "budget": {
      "score": 93,
      "critical": 0,
      "warning": 2,
      "info": 0,
      "totalIssues": 2,
      "weightedPenalty": 7
    },
    "links": {
      "score": 99,
      "critical": 0,
      "warning": 0,
      "info": 1,
      "totalIssues": 1,
      "weightedPenalty": 0.7
    },
    "dataQuality": {
      "score": 91,
      "critical": 0,
      "warning": 2,
      "info": 3,
      "totalIssues": 5,
      "weightedPenalty": 9.1
    },
    "rhythm": {
      "score": 97,
      "critical": 0,
      "warning": 1,
      "info": 0,
      "totalIssues": 1,
      "weightedPenalty": 3.5
    },
    "relevance": {
      "score": 96,
      "critical": 0,
      "warning": 1,
      "info": 1,
      "totalIssues": 2,
      "weightedPenalty": 4.2
    },
    "realism": {
      "score": 100,
      "critical": 0,
      "warning": 0,
      "info": 0,
      "totalIssues": 0,
      "weightedPenalty": 0
    }
  },
  "topRegressions": [
    {
      "key": "GEO_INTRA_DAY_ZIGZAG",
      "code": "GEO_INTRA_DAY_ZIGZAG",
      "category": "geography",
      "severity": "warning",
      "component": "pipeline/step8-validate",
      "count": 3,
      "impactScore": 21.6,
      "avgFrequencyWeight": 1.8,
      "autofixCandidate": true,
      "sampleMessages": [
        "Jour 1: itinéraire en zigzag (4 demi-tours détectés)",
        "Jour 2: itinéraire en zigzag (3 demi-tours détectés)",
        "Jour 3: itinéraire en zigzag (2 demi-tours détectés)"
      ]
    },
    {
      "key": "schedule:Jour 4: \"musées du Vatican\" (fin 17:20) chevauche \"Rome → Paris\" (débu",
      "category": "schedule",
      "severity": "critical",
      "count": 1,
      "impactScore": 10,
      "avgFrequencyWeight": 1,
      "autofixCandidate": false,
      "sampleMessages": [
        "Jour 4: \"musées du Vatican\" (fin 17:20) chevauche \"Rome → Paris\" (début 17:00)"
      ]
    },
    {
      "key": "GEO_DAY_ROUTE_EFFICIENCY_LOW",
      "code": "GEO_DAY_ROUTE_EFFICIENCY_LOW",
      "category": "geography",
      "severity": "warning",
      "component": "pipeline/step8-validate",
      "count": 1,
      "impactScore": 6,
      "avgFrequencyWeight": 1.5,
      "autofixCandidate": true,
      "sampleMessages": [
        "Jour 1: efficacité de route faible (1.96x du minimum MST)"
      ]
    },
    {
      "key": "budget:Pas d'hébergement défini dans le voyage",
      "category": "budget",
      "severity": "warning",
      "count": 1,
      "impactScore": 4,
      "avgFrequencyWeight": 1,
      "autofixCandidate": false,
      "sampleMessages": [
        "Pas d'hébergement défini dans le voyage"
      ]
    },
    {
      "key": "budget:Pas de costBreakdown dans le trip",
      "category": "budget",
      "severity": "warning",
      "count": 1,
      "impactScore": 4,
      "avgFrequencyWeight": 1,
      "autofixCandidate": false,
      "sampleMessages": [
        "Pas de costBreakdown dans le trip"
      ]
    },
    {
      "key": "data-quality:Pas d'hébergement défini",
      "category": "data-quality",
      "severity": "warning",
      "count": 1,
      "impactScore": 4,
      "avgFrequencyWeight": 1,
      "autofixCandidate": false,
      "sampleMessages": [
        "Pas d'hébergement défini"
      ]
    },
    {
      "key": "data-quality:Pas de breakdown des coûts",
      "category": "data-quality",
      "severity": "warning",
      "count": 1,
      "impactScore": 4,
      "avgFrequencyWeight": 1,
      "autofixCandidate": false,
      "sampleMessages": [
        "Pas de breakdown des coûts"
      ]
    },
    {
      "key": "relevance:Activité \"gastronomy\" demandée mais aucune activité correspondante tro",
      "category": "relevance",
      "severity": "warning",
      "count": 1,
      "impactScore": 4,
      "avgFrequencyWeight": 1,
      "autofixCandidate": false,
      "sampleMessages": [
        "Activité \"gastronomy\" demandée mais aucune activité correspondante trouvée dans l'itinéraire"
      ]
    },
    {
      "key": "rhythm:Jour 4: seulement 30min de temps libre — pas de pause",
      "category": "rhythm",
      "severity": "warning",
      "count": 1,
      "impactScore": 4,
      "avgFrequencyWeight": 1,
      "autofixCandidate": false,
      "sampleMessages": [
        "Jour 4: seulement 30min de temps libre — pas de pause"
      ]
    },
    {
      "key": "data-quality:Pas d'empreinte carbone calculée",
      "category": "data-quality",
      "severity": "info",
      "count": 1,
      "impactScore": 1,
      "avgFrequencyWeight": 1,
      "autofixCandidate": false,
      "sampleMessages": [
        "Pas d'empreinte carbone calculée"
      ]
    },
    {
      "key": "data-quality:Pas de conseils de voyage",
      "category": "data-quality",
      "severity": "info",
      "count": 1,
      "impactScore": 1,
      "avgFrequencyWeight": 1,
      "autofixCandidate": false,
      "sampleMessages": [
        "Pas de conseils de voyage"
      ]
    },
    {
      "key": "data-quality:Pas de vol aller défini (transport optimal/avion)",
      "category": "data-quality",
      "severity": "info",
      "count": 1,
      "impactScore": 1,
      "avgFrequencyWeight": 1,
      "autofixCandidate": false,
      "sampleMessages": [
        "Pas de vol aller défini (transport optimal/avion)"
      ]
    }
  ],
  "sections": {
    "schedule": [
      {
        "severity": "critical",
        "category": "schedule",
        "message": "Jour 4: \"musées du Vatican\" (fin 17:20) chevauche \"Rome → Paris\" (début 17:00)",
        "dayNumber": 4,
        "itemTitle": "musées du Vatican",
        "details": {
          "currentEnd": "17:20",
          "nextStart": "17:00",
          "overlapMinutes": 20
        }
      }
    ],
    "geography": [
      {
        "severity": "warning",
        "category": "geography",
        "message": "Jour 1: itinéraire en zigzag (4 demi-tours détectés)",
        "dayNumber": 1,
        "details": {
          "zigzagTurns": 4,
          "routeInefficiencyRatio": 1.96,
          "totalLegKm": 6.49
        },
        "code": "GEO_INTRA_DAY_ZIGZAG",
        "component": "pipeline/step8-validate",
        "frequencyWeight": 1.8,
        "autofixCandidate": true
      },
      {
        "severity": "warning",
        "category": "geography",
        "message": "Jour 1: efficacité de route faible (1.96x du minimum MST)",
        "dayNumber": 1,
        "details": {
          "routeInefficiencyRatio": 1.96,
          "threshold": 1.75,
          "totalLegKm": 6.49,
          "mstLowerBoundKm": 3.31
        },
        "code": "GEO_DAY_ROUTE_EFFICIENCY_LOW",
        "component": "pipeline/step8-validate",
        "frequencyWeight": 1.5,
        "autofixCandidate": true
      },
      {
        "severity": "warning",
        "category": "geography",
        "message": "Jour 2: itinéraire en zigzag (3 demi-tours détectés)",
        "dayNumber": 2,
        "details": {
          "zigzagTurns": 3,
          "routeInefficiencyRatio": 1.43,
          "totalLegKm": 2.25
        },
        "code": "GEO_INTRA_DAY_ZIGZAG",
        "component": "pipeline/step8-validate",
        "frequencyWeight": 1.8,
        "autofixCandidate": true
      },
      {
        "severity": "warning",
        "category": "geography",
        "message": "Jour 3: itinéraire en zigzag (2 demi-tours détectés)",
        "dayNumber": 3,
        "details": {
          "zigzagTurns": 2,
          "routeInefficiencyRatio": 1.62,
          "totalLegKm": 3.73
        },
        "code": "GEO_INTRA_DAY_ZIGZAG",
        "component": "pipeline/step8-validate",
        "frequencyWeight": 1.8,
        "autofixCandidate": true
      }
    ],
    "budget": [
      {
        "severity": "warning",
        "category": "budget",
        "message": "Pas de costBreakdown dans le trip"
      },
      {
        "severity": "warning",
        "category": "budget",
        "message": "Pas d'hébergement défini dans le voyage"
      }
    ],
    "links": [
      {
        "severity": "info",
        "category": "links",
        "message": "Jour 3: restaurant \"Petit-déjeuner — Repas libre\" n'a pas de lien Google Maps",
        "dayNumber": 3,
        "itemTitle": "Petit-déjeuner — Repas libre",
        "code": "LINK_RESTAURANT_MAPS_MISSING",
        "component": "pipeline/restaurants"
      }
    ],
    "dataQuality": [
      {
        "severity": "warning",
        "category": "data-quality",
        "message": "Pas d'hébergement défini"
      },
      {
        "severity": "info",
        "category": "data-quality",
        "message": "Pas d'empreinte carbone calculée"
      },
      {
        "severity": "warning",
        "category": "data-quality",
        "message": "Pas de breakdown des coûts"
      },
      {
        "severity": "info",
        "category": "data-quality",
        "message": "Pas de conseils de voyage"
      },
      {
        "severity": "info",
        "category": "data-quality",
        "message": "Pas de vol aller défini (transport optimal/avion)"
      }
    ],
    "rhythm": [
      {
        "severity": "warning",
        "category": "rhythm",
        "message": "Jour 4: seulement 30min de temps libre — pas de pause",
        "dayNumber": 4,
        "details": {
          "freeMinutes": 30,
          "occupiedMinutes": 895
        }
      }
    ],
    "relevance": [
      {
        "severity": "info",
        "category": "relevance",
        "message": "Tous les must-see présents (2/2)"
      },
      {
        "severity": "warning",
        "category": "relevance",
        "message": "Activité \"gastronomy\" demandée mais aucune activité correspondante trouvée dans l'itinéraire",
        "details": {
          "requestedActivity": "gastronomy"
        }
      }
    ],
    "realism": []
  },
  "stats": {
    "totalDays": 4,
    "totalItems": 39,
    "activitiesCount": 14,
    "restaurantsCount": 11,
    "avgItemsPerDay": 9.75,
    "totalEstimatedCost": null,
    "hasAccommodation": false,
    "hasOutboundFlight": false,
    "hasReturnFlight": false,
    "hasCarbonFootprint": false
  }
}