{
  "tripId": "6aa19b11-2f12-4610-b205-041529d69aa5",
  "scenarioId": "geo-direct-02",
  "generatedAt": "2026-02-17T13:07:43.721Z",
  "destination": "Marrakech",
  "summary": {
    "totalIssues": 15,
    "critical": 2,
    "warning": 5,
    "info": 8,
    "score": 90,
    "weightedScore": 90
  },
  "sectionScores": {
    "schedule": {
      "score": 100,
      "critical": 0,
      "warning": 0,
      "info": 0,
      "totalIssues": 0,
      "weightedPenalty": 0
    },
    "geography": {
      "score": 38,
      "critical": 2,
      "warning": 5,
      "info": 0,
      "totalIssues": 7,
      "weightedPenalty": 62.45
    },
    "budget": {
      "score": 100,
      "critical": 0,
      "warning": 0,
      "info": 0,
      "totalIssues": 0,
      "weightedPenalty": 0
    },
    "links": {
      "score": 100,
      "critical": 0,
      "warning": 0,
      "info": 0,
      "totalIssues": 0,
      "weightedPenalty": 0
    },
    "dataQuality": {
      "score": 95,
      "critical": 0,
      "warning": 0,
      "info": 7,
      "totalIssues": 7,
      "weightedPenalty": 4.9
    },
    "rhythm": {
      "score": 99,
      "critical": 0,
      "warning": 0,
      "info": 1,
      "totalIssues": 1,
      "weightedPenalty": 0.7
    },
    "relevance": {
      "score": 100,
      "critical": 0,
      "warning": 0,
      "info": 0,
      "totalIssues": 0,
      "weightedPenalty": 0
    },
    "realism": {
      "score": 100,
      "critical": 0,
      "warning": 0,
      "info": 0,
      "totalIssues": 0,
      "weightedPenalty": 0
    }
  },
  "topRegressions": [
    {
      "key": "GEO_INTRA_DAY_ZIGZAG",
      "code": "GEO_INTRA_DAY_ZIGZAG",
      "category": "geography",
      "severity": "warning",
      "component": "pipeline/step8-validate",
      "count": 4,
      "impactScore": 28.8,
      "avgFrequencyWeight": 1.8,
      "autofixCandidate": true,
      "sampleMessages": [
        "Jour 2: itinéraire en zigzag (4 demi-tours détectés)",
        "Jour 3: itinéraire en zigzag (4 demi-tours détectés)",
        "Jour 4: itinéraire en zigzag (3 demi-tours détectés)"
      ]
    },
    {
      "key": "GEO_URBAN_HARD_LONG_LEG",
      "code": "GEO_URBAN_HARD_LONG_LEG",
      "category": "geography",
      "severity": "critical",
      "component": "pipeline/step8-validate",
      "count": 1,
      "impactScore": 22,
      "avgFrequencyWeight": 2.2,
      "autofixCandidate": true,
      "sampleMessages": [
        "Jour 5: segment urbain dur 4.2km entre \"Déjeuner — La Table de la Kasbah\" et \"Musée d’Art Contemporain Africain Al Maaden (MACAAL)\" (> 4km)"
      ]
    },
    {
      "key": "geography:Jour 5: \"Trajet vers RAK + check-in\" a des coordonnées (0, 0) — non gé",
      "category": "geography",
      "severity": "critical",
      "count": 1,
      "impactScore": 10,
      "avgFrequencyWeight": 1,
      "autofixCandidate": false,
      "sampleMessages": [
        "Jour 5: \"Trajet vers RAK + check-in\" a des coordonnées (0, 0) — non géocodé"
      ]
    },
    {
      "key": "DATA_ACTIVITY_DESCRIPTION_MISSING",
      "code": "DATA_ACTIVITY_DESCRIPTION_MISSING",
      "category": "data-quality",
      "severity": "info",
      "component": "pipeline/content",
      "count": 6,
      "impactScore": 6,
      "avgFrequencyWeight": 1,
      "autofixCandidate": false,
      "sampleMessages": [
        "Jour 1: \"Jungle Rooftop La Pergola - Jazz Bar & Restaurant\" n'a pas de description",
        "Jour 4: \"The Beautiful Marrakech | Excursions, Balades, Piscines et Bien Plus Encore Avec Notre Agence\" n'a pas de description",
        "Jour 4: \"Jardin Majorelle\" n'a pas de description"
      ]
    },
    {
      "key": "GEO_DAY_ROUTE_EFFICIENCY_LOW",
      "code": "GEO_DAY_ROUTE_EFFICIENCY_LOW",
      "category": "geography",
      "severity": "warning",
      "component": "pipeline/step8-validate",
      "count": 1,
      "impactScore": 6,
      "avgFrequencyWeight": 1.5,
      "autofixCandidate": true,
      "sampleMessages": [
        "Jour 2: efficacité de route faible (1.95x du minimum MST)"
      ]
    },
    {
      "key": "data-quality:Pas d'empreinte carbone calculée",
      "category": "data-quality",
      "severity": "info",
      "count": 1,
      "impactScore": 1,
      "avgFrequencyWeight": 1,
      "autofixCandidate": false,
      "sampleMessages": [
        "Pas d'empreinte carbone calculée"
      ]
    },
    {
      "key": "rhythm:Jour 1 (2 activités) vs jour 2 (7 activités) — déséquilibre important",
      "category": "rhythm",
      "severity": "info",
      "count": 1,
      "impactScore": 1,
      "avgFrequencyWeight": 1,
      "autofixCandidate": false,
      "sampleMessages": [
        "Jour 1 (2 activités) vs jour 2 (7 activités) — déséquilibre important"
      ]
    }
  ],
  "sections": {
    "schedule": [],
    "geography": [
      {
        "severity": "warning",
        "category": "geography",
        "message": "Jour 2: itinéraire en zigzag (4 demi-tours détectés)",
        "dayNumber": 2,
        "details": {
          "zigzagTurns": 4
        },
        "code": "GEO_INTRA_DAY_ZIGZAG",
        "component": "pipeline/step8-validate",
        "frequencyWeight": 1.8,
        "autofixCandidate": true
      },
      {
        "severity": "warning",
        "category": "geography",
        "message": "Jour 2: efficacité de route faible (1.95x du minimum MST)",
        "dayNumber": 2,
        "details": {
          "routeInefficiencyRatio": 1.95,
          "threshold": 1.75,
          "totalLegKm": 2.95,
          "mstLowerBoundKm": 1.52
        },
        "code": "GEO_DAY_ROUTE_EFFICIENCY_LOW",
        "component": "pipeline/step8-validate",
        "frequencyWeight": 1.5,
        "autofixCandidate": true
      },
      {
        "severity": "warning",
        "category": "geography",
        "message": "Jour 3: itinéraire en zigzag (4 demi-tours détectés)",
        "dayNumber": 3,
        "details": {
          "zigzagTurns": 4
        },
        "code": "GEO_INTRA_DAY_ZIGZAG",
        "component": "pipeline/step8-validate",
        "frequencyWeight": 1.8,
        "autofixCandidate": true
      },
      {
        "severity": "warning",
        "category": "geography",
        "message": "Jour 4: itinéraire en zigzag (3 demi-tours détectés)",
        "dayNumber": 4,
        "details": {
          "zigzagTurns": 3
        },
        "code": "GEO_INTRA_DAY_ZIGZAG",
        "component": "pipeline/step8-validate",
        "frequencyWeight": 1.8,
        "autofixCandidate": true
      },
      {
        "severity": "critical",
        "category": "geography",
        "message": "Jour 5: \"Trajet vers RAK + check-in\" a des coordonnées (0, 0) — non géocodé",
        "dayNumber": 5,
        "itemTitle": "Trajet vers RAK + check-in"
      },
      {
        "severity": "critical",
        "category": "geography",
        "message": "Jour 5: segment urbain dur 4.2km entre \"Déjeuner — La Table de la Kasbah\" et \"Musée d’Art Contemporain Africain Al Maaden (MACAAL)\" (> 4km)",
        "dayNumber": 5,
        "details": {
          "distanceKm": 4.22,
          "thresholdKm": 4
        },
        "code": "GEO_URBAN_HARD_LONG_LEG",
        "component": "pipeline/step8-validate",
        "frequencyWeight": 2.2,
        "autofixCandidate": true
      },
      {
        "severity": "warning",
        "category": "geography",
        "message": "Jour 5: itinéraire en zigzag (2 demi-tours détectés)",
        "dayNumber": 5,
        "details": {
          "zigzagTurns": 2
        },
        "code": "GEO_INTRA_DAY_ZIGZAG",
        "component": "pipeline/step8-validate",
        "frequencyWeight": 1.8,
        "autofixCandidate": true
      }
    ],
    "budget": [],
    "links": [],
    "dataQuality": [
      {
        "severity": "info",
        "category": "data-quality",
        "message": "Pas d'empreinte carbone calculée"
      },
      {
        "severity": "info",
        "category": "data-quality",
        "message": "Jour 1: \"Jungle Rooftop La Pergola - Jazz Bar & Restaurant\" n'a pas de description",
        "dayNumber": 1,
        "itemTitle": "Jungle Rooftop La Pergola - Jazz Bar & Restaurant",
        "code": "DATA_ACTIVITY_DESCRIPTION_MISSING",
        "component": "pipeline/content"
      },
      {
        "severity": "info",
        "category": "data-quality",
        "message": "Jour 4: \"The Beautiful Marrakech | Excursions, Balades, Piscines et Bien Plus Encore Avec Notre Agence\" n'a pas de description",
        "dayNumber": 4,
        "itemTitle": "The Beautiful Marrakech | Excursions, Balades, Piscines et Bien Plus Encore Avec Notre Agence",
        "code": "DATA_ACTIVITY_DESCRIPTION_MISSING",
        "component": "pipeline/content"
      },
      {
        "severity": "info",
        "category": "data-quality",
        "message": "Jour 4: \"Jardin Majorelle\" n'a pas de description",
        "dayNumber": 4,
        "itemTitle": "Jardin Majorelle",
        "code": "DATA_ACTIVITY_DESCRIPTION_MISSING",
        "component": "pipeline/content"
      },
      {
        "severity": "info",
        "category": "data-quality",
        "message": "Jour 4: \"Place Jemaa el fna\" n'a pas de description",
        "dayNumber": 4,
        "itemTitle": "Place Jemaa el fna",
        "code": "DATA_ACTIVITY_DESCRIPTION_MISSING",
        "component": "pipeline/content"
      },
      {
        "severity": "info",
        "category": "data-quality",
        "message": "Jour 5: \"Palais El Badiî\" n'a pas de description",
        "dayNumber": 5,
        "itemTitle": "Palais El Badiî",
        "code": "DATA_ACTIVITY_DESCRIPTION_MISSING",
        "component": "pipeline/content"
      },
      {
        "severity": "info",
        "category": "data-quality",
        "message": "Jour 5: \"Musée d’Art Contemporain Africain Al Maaden (MACAAL)\" n'a pas de description",
        "dayNumber": 5,
        "itemTitle": "Musée d’Art Contemporain Africain Al Maaden (MACAAL)",
        "code": "DATA_ACTIVITY_DESCRIPTION_MISSING",
        "component": "pipeline/content"
      }
    ],
    "rhythm": [
      {
        "severity": "info",
        "category": "rhythm",
        "message": "Jour 1 (2 activités) vs jour 2 (7 activités) — déséquilibre important",
        "details": {
          "day1": 2,
          "day2": 7
        }
      }
    ],
    "relevance": [],
    "realism": []
  },
  "stats": {
    "totalDays": 5,
    "totalItems": 35,
    "activitiesCount": 17,
    "restaurantsCount": 12,
    "avgItemsPerDay": 7,
    "totalEstimatedCost": 1178,
    "hasAccommodation": true,
    "hasOutboundFlight": true,
    "hasReturnFlight": true,
    "hasCarbonFootprint": false
  }
}